{
    "meta": {
        "img_id": "나무_7_남_A037_lhw_20220901_14570100_0217",
        "contributor": "A037",
        "date_created": "2022-09-21",
        "img_path": "../../원천데이터/나무/나무_7_남_00710.jpg",
        "label_path": "./나무_7_남_00710.json",
        "img_size": 71683,
        "img_resolution": "1280x1280",
        "age": 7,
        "sex": "남"
    },
    "annotations": {
        "anno_id": "s5xyojvvh0lgb3euq69xlw",
        "class": "나무",
        "bbox_count": 18,
        "bbox": [
            {
                "label": "나무전체",
                "x": 393,
                "y": 11,
                "w": 582,
                "h": 870
            },
            {
                "label": "기둥",
                "x": 493,
                "y": 285,
                "w": 349,
                "h": 499
            },
            {
                "label": "수관",
                "x": 393,
                "y": 10,
                "w": 586,
                "h": 364
            },
            {
                "label": "가지",
                "x": 481,
                "y": 84,
                "w": 363,
                "h": 220
            },
            {
                "label": "뿌리",
                "x": 468,
                "y": 738,
                "w": 391,
                "h": 142
            },
            {
                "label": "나뭇잎",
                "x": 612,
                "y": 38,
                "w": 66,
                "h": 104
            },
            {
                "label": "나뭇잎",
                "x": 781,
                "y": 69,
                "w": 70,
                "h": 89
            },
            {
                "label": "꽃",
                "x": 948,
                "y": 563,
                "w": 173,
                "h": 242
            },
            {
                "label": "꽃",
                "x": 223,
                "y": 550,
                "w": 144,
                "h": 225
            },
            {
                "label": "열매",
                "x": 425,
                "y": 201,
                "w": 63,
                "h": 86
            },
            {
                "label": "열매",
                "x": 789,
                "y": 211,
                "w": 97,
                "h": 127
            },
            {
                "label": "그네",
                "x": 827,
                "y": 295,
                "w": 119,
                "h": 329
            },
            {
                "label": "새",
                "x": 999,
                "y": 267,
                "w": 205,
                "h": 217
            },
            {
                "label": "다람쥐",
                "x": 591,
                "y": 459,
                "w": 82,
                "h": 141
            },
            {
                "label": "구름",
                "x": 116,
                "y": 192,
                "w": 268,
                "h": 216
            },
            {
                "label": "달",
                "x": 1084,
                "y": 4,
                "w": 117,
                "h": 275
            },
            {
                "label": "별",
                "x": 939,
                "y": 17,
                "w": 127,
                "h": 168
            },
            {
                "label": "별",
                "x": 185,
                "y": 100,
                "w": 68,
                "h": 136
            }
        ]
    },
    "shape_description": {
        "prop_obj_img": [
            [
                0.30904541015625
            ],
            [
                0.1062933349609375
            ],
            [
                0.1301904296875
            ],
            [
                0.04874267578125
            ],
            [
                0.033887939453125
            ],
            [
                0.004189453125,
                0.003802490234375
            ],
            [
                0.025552978515625,
                0.019775390625
            ],
            [
                0.003306884765625,
                0.0075189208984375
            ],
            [
                0.0238958740234375
            ],
            [
                0.0271514892578125
            ],
            [
                0.007056884765625
            ],
            [
                0.03533203125
            ],
            [
                0.0196380615234375
            ],
            [
                0.0130224609375,
                0.00564453125
            ]
        ],
        "prop_obj_cls": [
            [
                1.0
            ],
            [
                0.34394083027214917
            ],
            [
                0.42126634277363034
            ],
            [
                0.15772010901765612
            ],
            [
                0.10965359244776238
            ],
            [
                0.01355610854366631,
                0.012303985464312517
            ],
            [
                0.08268357230319548,
                0.06398862424457874
            ],
            [
                0.010700319943121223,
                0.02432950191570881
            ],
            [
                0.0773215625864044
            ],
            [
                0.08785598609629892
            ],
            [
                0.02283445905913023
            ],
            [
                0.11432634198364736
            ],
            [
                0.06354425879843584
            ],
            [
                0.04213769403957815,
                0.01826440731524272
            ]
        ],
        "num_obj": [
            1,
            1,
            1,
            1,
            1,
            2,
            2,
            2,
            1,
            1,
            1,
            1,
            1,
            2
        ],
        "centroid_cls": [
            0.5350058247848952,
            0.34884669142839353
        ]
    }
}